[
  {
    "id": "EQ001",
    "name": "CMP Blow Moulding Machine – 5L Single Head",
    "type": "Machine",
    "make": "CMP",
    "model": "[TO BE ENTERED]",
    "serial_no": "[TO BE ENTERED]",
    "location": "Production Floor",
    "capacity_or_range": "5L single head",
    "date_commissioned": "[TO BE ENTERED]",
    "calibration_due": null,
    "calibration_frequency_months": null,
    "maintenance_frequency_months": 3,
    "responsible_role_id": "R003",
    "status": "Active"
  },
  {
    "id": "EQ002",
    "name": "CMP Blow Moulding Machine – 1L Double Head",
    "type": "Machine",
    "make": "CMP",
    "model": "[TO BE ENTERED]",
    "serial_no": "[TO BE ENTERED]",
    "location": "Production Floor",
    "capacity_or_range": "1L double head",
    "date_commissioned": "[TO BE ENTERED]",
    "calibration_due": null,
    "calibration_frequency_months": null,
    "maintenance_frequency_months": 3,
    "responsible_role_id": "R003",
    "status": "Active"
  },
  {
    "id": "EQ003",
    "name": "CMP Blow Moulding Machine – 200ml Double Head",
    "type": "Machine",
    "make": "CMP",
    "model": "[TO BE ENTERED]",
    "serial_no": "[TO BE ENTERED]",
    "location": "Production Floor",
    "capacity_or_range": "200ml double head",
    "date_commissioned": "[TO BE ENTERED]",
    "calibration_due": null,
    "calibration_frequency_months": null,
    "maintenance_frequency_months": 3,
    "responsible_role_id": "R003",
    "status": "Active"
  },
  {
    "id": "EQ004",
    "name": "CMP Blow Moulding Machine – 100ml Double Head",
    "type": "Machine",
    "make": "CMP",
    "model": "[TO BE ENTERED]",
    "serial_no": "[TO BE ENTERED]",
    "location": "Production Floor",
    "capacity_or_range": "100ml double head",
    "date_commissioned": "[TO BE ENTERED]",
    "calibration_due": null,
    "calibration_frequency_months": null,
    "maintenance_frequency_months": 3,
    "responsible_role_id": "R003",
    "status": "Active"
  },
  {
    "id": "EQ005",
    "name": "Vernier Caliper",
    "type": "Instrument",
    "make": "[TO BE ENTERED]",
    "model": "[TO BE ENTERED]",
    "serial_no": "[TO BE ENTERED]",
    "location": "QC Lab",
    "capacity_or_range": "0–300 mm",
    "date_commissioned": "[TO BE ENTERED]",
    "calibration_due": "[TO BE ENTERED]",
    "calibration_frequency_months": 12,
    "maintenance_frequency_months": null,
    "responsible_role_id": "R004",
    "status": "Active"
  },
  {
    "id": "EQ006",
    "name": "Wall Thickness Gauge (Ultrasonic)",
    "type": "Instrument",
    "make": "[TO BE ENTERED]",
    "model": "[TO BE ENTERED]",
    "serial_no": "[TO BE ENTERED]",
    "location": "QC Lab",
    "capacity_or_range": "0–20 mm",
    "date_commissioned": "[TO BE ENTERED]",
    "calibration_due": "[TO BE ENTERED]",
    "calibration_frequency_months": 12,
    "maintenance_frequency_months": null,
    "responsible_role_id": "R004",
    "status": "Active"
  },
  {
    "id": "EQ007",
    "name": "Weighing Scale – RM Store",
    "type": "Instrument",
    "make": "[TO BE ENTERED]",
    "model": "[TO BE ENTERED]",
    "serial_no": "[TO BE ENTERED]",
    "location": "RM Store",
    "capacity_or_range": "0–100 kg",
    "date_commissioned": "[TO BE ENTERED]",
    "calibration_due": "[TO BE ENTERED]",
    "calibration_frequency_months": 6,
    "maintenance_frequency_months": null,
    "responsible_role_id": "R006",
    "status": "Active"
  },
  {
    "id": "EQ008",
    "name": "Weighing Scale – QC",
    "type": "Instrument",
    "make": "[TO BE ENTERED]",
    "model": "[TO BE ENTERED]",
    "serial_no": "[TO BE ENTERED]",
    "location": "QC Lab",
    "capacity_or_range": "0–5 kg",
    "date_commissioned": "[TO BE ENTERED]",
    "calibration_due": "[TO BE ENTERED]",
    "calibration_frequency_months": 6,
    "maintenance_frequency_months": null,
    "responsible_role_id": "R004",
    "status": "Active"
  },
  {
    "id": "EQ009",
    "name": "Pressure Gauge",
    "type": "Instrument",
    "make": "[TO BE ENTERED]",
    "model": "[TO BE ENTERED]",
    "serial_no": "[TO BE ENTERED]",
    "location": "Production Floor",
    "capacity_or_range": "0–10 bar",
    "date_commissioned": "[TO BE ENTERED]",
    "calibration_due": "[TO BE ENTERED]",
    "calibration_frequency_months": 12,
    "maintenance_frequency_months": null,
    "responsible_role_id": "R003",
    "status": "Active"
  },
  {
    "id": "EQ010",
    "name": "Temperature Gun (IR Thermometer)",
    "type": "Instrument",
    "make": "[TO BE ENTERED]",
    "model": "[TO BE ENTERED]",
    "serial_no": "[TO BE ENTERED]",
    "location": "Production Floor",
    "capacity_or_range": "-50 to +550 °C",
    "date_commissioned": "[TO BE ENTERED]",
    "calibration_due": "[TO BE ENTERED]",
    "calibration_frequency_months": 12,
    "maintenance_frequency_months": null,
    "responsible_role_id": "R003",
    "status": "Active"
  },
  {
    "id": "EQ011",
    "name": "Torque Tester (Cap / Closure)",
    "type": "Instrument",
    "make": "[TO BE ENTERED]",
    "model": "[TO BE ENTERED]",
    "serial_no": "[TO BE ENTERED]",
    "location": "QC Lab",
    "capacity_or_range": "0–5 Nm",
    "date_commissioned": "[TO BE ENTERED]",
    "calibration_due": "[TO BE ENTERED]",
    "calibration_frequency_months": 12,
    "maintenance_frequency_months": null,
    "responsible_role_id": "R004",
    "status": "Active"
  },
  {
    "id": "EQ012",
    "name": "pH Meter",
    "type": "Instrument",
    "make": "[TO BE ENTERED]",
    "model": "[TO BE ENTERED]",
    "serial_no": "[TO BE ENTERED]",
    "location": "QC Lab",
    "capacity_or_range": "0–14 pH",
    "date_commissioned": "[TO BE ENTERED]",
    "calibration_due": "[TO BE ENTERED]",
    "calibration_frequency_months": 12,
    "maintenance_frequency_months": null,
    "responsible_role_id": "R004",
    "status": "Active"
  }
]
